gr11prctl/__init__.py
gr11prctl/index.py
gr11prctl/snippets.py
gr11prctl-0.0.3.dist-info/METADATA
gr11prctl-0.0.3.dist-info/WHEEL
gr11prctl-0.0.3.dist-info/top_level.txt
gr11prctl-0.0.3.dist-info/RECORD
