Metadata-Version: 2.2
Name: gr11prctl
Version: 0.0.3
Summary: A Python package for Grade 11 practical programs.
Home-page: https://github.com/TanujairamV/gr11prctl
Author: Tanujairam
Author-email: tanujairam.v@gmail.com
Classifier: Programming Language :: Python :: 3
Classifier: License :: OSI Approved :: MIT License
Classifier: Operating System :: OS Independent
Requires-Python: >=3.6
Dynamic: author
Dynamic: author-email
Dynamic: classifier
Dynamic: description
Dynamic: description-content-type
Dynamic: home-page
Dynamic: requires-python
Dynamic: summary
